{
	"nodes":[
		{"id":"injury superficial head"},
		{"id":"cerebrovascular apoplexy"},
		{"id":"developmental reading disorder"},
		{"id":"unilateral headaches"},
		{"id":"hepatitides"},
		{"id":"hiv infections"},
		{"id":"gunshot wounds"},
		{"id":"emesis"},
		{"id":"sclerosis"},
		{"id":"body weight"},
		{"id":"diseases infectious"},
		{"id":"back injuries"},
		{"id":"anemias"},
		{"id":"obesity"},
		{"id":"spasms"},
		{"id":"strain"},
		{"id":"trauma"},
		{"id":"injury wrist"},
		{"id":"diseases nervous system"},
		{"id":"leanness"},
		{"id":"pulmonary cancer"},
		{"id":"hiccups"},
		{"id":"sleep hypopneas"},
		{"id":"hyperthermia"},
		{"id":"defects congenital"},
		{"id":"stress water"},
		{"id":"rheumatoid arthritis"},
		{"id":"anthrax"},
		{"id":"bruises"},
		{"id":"leg injuries"},
		{"id":"recurrence"},
		{"id":"chronic alcoholic intoxication"},
		{"id":"bone fractures"},
		{"id":"fibrocystic disease of pancreas"},
		{"id":"dizzyness"},
		{"id":"fibrosis"},
		{"id":"melanomas malignant"},
		{"id":"cancer colon"},
		{"id":"reactive confusion"},
		{"id":"malignant neoplasm of breast"},
		{"id":"heart attacks"},
		{"id":"infection"},
		{"id":"cramps muscular"},
		{"id":"cancer prostatic"},
		{"id":"pt-nanbh"},
		{"id":"knee injury"},
		{"id":"disseminated sclerosis"},
		{"id":"breakbone fever"},
		{"id":"neoplasms skin"},
		{"id":"polyarthritides"},
		{"id":"paralysis todd's"},
		{"id":"inflammation"},
		{"id":"heart disease"},
		{"id":"cadaver"},
		{"id":"overweight"},
		{"id":"microcephaly"},
		{"id":"injury ankle"},
		{"id":"bullous lesion"},
		{"id":"syndrome acquired immuno-deficiency"},
		{"id":"disease"},
		{"id":"apnea"},
		{"id":"blood pressures high"},
		{"id":"developmental stuttering"},
		{"id":"tumors"},
		{"id":"cardiac death"},
		{"id":"injuries foot"},
		{"id":"diarrheas"}
	],
	"links":[
		{"source":"disseminated sclerosis","target":"sclerosis","value":4},
		{"source":"apnea","target":"sleep hypopneas","value":8},
		{"source":"hepatitides","target":"pt-nanbh","value":9},
		{"source":"defects congenital","target":"microcephaly","value":14},
		{"source":"bruises","target":"spasms","value":20},
		{"source":"injury ankle","target":"knee injury","value":20},
		{"source":"bruises","target":"inflammation","value":21},
		{"source":"inflammation","target":"spasms","value":23},
		{"source":"injuries foot","target":"knee injury","value":25},
		{"source":"inflammation","target":"strain","value":26},
		{"source":"injuries foot","target":"injury ankle","value":26},
		{"source":"knee injury","target":"trauma","value":26},
		{"source":"emesis","target":"hyperthermia","value":27},
		{"source":"injury ankle","target":"trauma","value":30},
		{"source":"diseases infectious","target":"hyperthermia","value":31},
		{"source":"knee injury","target":"leg injuries","value":32},
		{"source":"injury ankle","target":"leg injuries","value":32},
		{"source":"disease","target":"diseases infectious","value":35},
		{"source":"bone fractures","target":"inflammation","value":35},
		{"source":"bruises","target":"strain","value":36},
		{"source":"polyarthritides","target":"rheumatoid arthritis","value":37},
		{"source":"spasms","target":"strain","value":37},
		{"source":"malignant neoplasm of breast","target":"tumors","value":38},
		{"source":"injuries foot","target":"leg injuries","value":38},
		{"source":"disease","target":"hyperthermia","value":38},
		{"source":"injuries foot","target":"trauma","value":39},
		{"source":"bone fractures","target":"bruises","value":39},
		{"source":"leg injuries","target":"trauma","value":40},
		{"source":"back injuries","target":"trauma","value":41},
		{"source":"diseases infectious","target":"emesis","value":42},
		{"source":"bone fractures","target":"spasms","value":42},
		{"source":"diseases nervous system","target":"microcephaly","value":43},
		{"source":"disease","target":"emesis","value":44},
		{"source":"defects congenital","target":"diseases nervous system","value":45},
		{"source":"diarrheas","target":"emesis","value":46},
		{"source":"diarrheas","target":"disease","value":48},
		{"source":"leanness","target":"overweight","value":49},
		{"source":"fibrocystic disease of pancreas","target":"fibrosis","value":49},
		{"source":"cramps muscular","target":"inflammation","value":50},
		{"source":"breakbone fever","target":"microcephaly","value":51},
		{"source":"back injuries","target":"injury ankle","value":51},
		{"source":"blood pressures high","target":"heart disease","value":52},
		{"source":"cancer prostatic","target":"tumors","value":52},
		{"source":"injury superficial head","target":"trauma","value":52},
		{"source":"heart attacks","target":"heart disease","value":52},
		{"source":"diseases infectious","target":"infection","value":52},
		{"source":"back injuries","target":"knee injury","value":54},
		{"source":"bone fractures","target":"strain","value":54},
		{"source":"bruises","target":"trauma","value":54},
		{"source":"diarrheas","target":"hyperthermia","value":54},
		{"source":"heart disease","target":"overweight","value":55},
		{"source":"cerebrovascular apoplexy","target":"heart disease","value":55},
		{"source":"cramps muscular","target":"strain","value":56},
		{"source":"spasms","target":"trauma","value":56},
		{"source":"anthrax","target":"cramps muscular","value":58},
		{"source":"breakbone fever","target":"defects congenital","value":58},
		{"source":"hiv infections","target":"syndrome acquired immuno-deficiency","value":58},
		{"source":"bone fractures","target":"stress water","value":58},
		{"source":"cerebrovascular apoplexy","target":"heart attacks","value":59},
		{"source":"hyperthermia","target":"infection","value":59},
		{"source":"disease","target":"infection","value":60},
		{"source":"recurrence","target":"tumors","value":60},
		{"source":"pulmonary cancer","target":"tumors","value":60},
		{"source":"overweight","target":"tumors","value":60},
		{"source":"reactive confusion","target":"unilateral headaches","value":60},
		{"source":"cerebrovascular apoplexy","target":"overweight","value":60},
		{"source":"diarrheas","target":"diseases infectious","value":60},
		{"source":"melanomas malignant","target":"neoplasms skin","value":61},
		{"source":"cardiac death","target":"reactive confusion","value":61},
		{"source":"bruises","target":"cramps muscular","value":61},
		{"source":"cancer colon","target":"tumors","value":61},
		{"source":"bruises","target":"injury wrist","value":61},
		{"source":"blood pressures high","target":"heart attacks","value":62},
		{"source":"blood pressures high","target":"cerebrovascular apoplexy","value":62},
		{"source":"cardiac death","target":"gunshot wounds","value":62},
		{"source":"cadaver","target":"cardiac death","value":62},
		{"source":"back injuries","target":"injuries foot","value":62},
		{"source":"back injuries","target":"spasms","value":62},
		{"source":"heart attacks","target":"overweight","value":62},
		{"source":"bullous lesion","target":"injury wrist","value":62},
		{"source":"hiccups","target":"reactive confusion","value":62},
		{"source":"back injuries","target":"bruises","value":63},
		{"source":"pt-nanbh","target":"trauma","value":63},
		{"source":"obesity","target":"overweight","value":63},
		{"source":"anemias","target":"chronic alcoholic intoxication","value":63},
		{"source":"bruises","target":"bullous lesion","value":63},
		{"source":"developmental stuttering","target":"trauma","value":63},
		{"source":"obesity","target":"tumors","value":63},
		{"source":"inflammation","target":"stress water","value":63},
		{"source":"injury wrist","target":"spasms","value":64},
		{"source":"heart attacks","target":"syndrome acquired immuno-deficiency","value":64},
		{"source":"heart disease","target":"tumors","value":64},
		{"source":"blood pressures high","target":"body weight","value":64},
		{"source":"paralysis todd's","target":"reactive confusion","value":64},
		{"source":"developmental reading disorder","target":"trauma","value":64},
		{"source":"injury superficial head","target":"knee injury","value":64},
		{"source":"dizzyness","target":"inflammation","value":64},
		{"source":"anemias","target":"heart attacks","value":64},
		{"source":"bruises","target":"stress water","value":64},
		{"source":"developmental reading disorder","target":"injury ankle","value":64}
	]
}
